{"cameraMode":{"drawMode":0,"name":"Shaded","section":"Shading Mode"},"sceneLighting":true,"audioPlay":false,"sceneViewState":{"m_AlwaysRefresh":false,"showFog":true,"showSkybox":true,"showFlares":true,"showImageEffects":true,"showParticleSystems":true,"showVisualEffectGraphs":true,"m_FxEnabled":true},"in2DMode":false,"pivot":{"x":439.68280029296877,"y":504.3989562988281,"z":-262.35162353515627},"rotation":{"x":0.032993629574775699,"y":-0.004497593268752098,"z":0.00014847447164356709,"w":0.9994430541992188},"size":313.9779357910156,"orthographic":false}